LICENSE
MANIFEST.in
README.rst
setup.py
tox.ini
clouddistrict/__init__.py
clouddistrict/building.py
clouddistrict/family.py
clouddistrict/job.py
clouddistrict/namerator.py
clouddistrict/npc.py
clouddistrict/race.py
clouddistrict/residence.py
clouddistrict/town.py
clouddistrict/util.py
clouddistrict.egg-info/PKG-INFO
clouddistrict.egg-info/SOURCES.txt
clouddistrict.egg-info/dependency_links.txt
clouddistrict.egg-info/entry_points.txt
clouddistrict.egg-info/not-zip-safe
clouddistrict.egg-info/requires.txt
clouddistrict.egg-info/top_level.txt
clouddistrict/.ropeproject/config.py
clouddistrict/names/dwarf.txt
clouddistrict/names/dwarf_part1.txt
clouddistrict/names/dwarf_part2.txt
clouddistrict/names/elf.txt
clouddistrict/names/halfling_last.txt
clouddistrict/names/human_first_female.txt
clouddistrict/names/human_first_male.txt
clouddistrict/names/human_last.txt
clouddistrict/names/orc.txt