Metadata-Version: 1.1
Name: clouddistrict
Version: 0.0.4
Summary: Generate occupants and occupations for your custom village, town or city! (for D&D purposes or related) (please do not imbibe clouddistrict while under the influence of other medications)
Home-page: https://www.bitbucket.org/johannestaas/clouddistrict
Author: Johan Nestaas
Author-email: johannestaas@gmail.com
License: GPLv3+
Platform: UNKNOWN
Classifier: Development Status :: 3 - Alpha
Classifier: License :: OSI Approved :: GNU General Public License v3 or later (GPLv3+)
Classifier: Environment :: Console
Classifier: Environment :: X11 Applications :: Qt
Classifier: Environment :: MacOS X
Classifier: Environment :: Win32 (MS Windows)
Classifier: Operating System :: POSIX
Classifier: Operating System :: MacOS :: MacOS X
Classifier: Operating System :: Microsoft :: Windows
Classifier: Programming Language :: Python
